{"SpawnDistance":5000,"Points":{"XB4-275":{"pid":"XB4-S","t":"GASPLANET","wic":{},"woc":{},"wgc":{},"sig":[{"TypeName":"0-2","SigString":"","Dev":{"X":-0.23624658995333545,"Y":-0.3130481512736557}},{"TypeName":"1-3","SigString":"","Dev":{"X":0.3185124320757248,"Y":-0.570414599623114}},{"TypeName":"3-1","SigString":"","Dev":{"X":-0.04199562633571771,"Y":0.0937370691090951}},{"TypeName":"6-2","SigString":"","Dev":{"X":0.4629839531416306,"Y":0.47440910489663346}},{"TypeName":"7-2","SigString":"","Dev":{"X":0.9197504289282407,"Y":0.05516580423183142}},{"TypeName":"7-3","SigString":"","Dev":{"X":-0.12092775996287801,"Y":-0.3544052442689824}},{"TypeName":"8-1","SigString":"","Dev":{"X":0.6027245276142317,"Y":-0.35591126755383495}},{"TypeName":"10-1","SigString":"","Dev":{"X":0.6658875295652529,"Y":0.5771017440156989}},{"TypeName":"11-1","SigString":"","Dev":{"X":0.7121861812449083,"Y":-0.3916826550250467}}],"clr":{"R":208,"G":254,"B":241,"A":255}},"XB4-S":{"t":"STAR","wic":{},"woc":{},"wgc":{},"clr":{"R":252,"G":234,"B":207,"A":255}}}}