{"SpawnDistance":5000,"Points":{"GW6-524":{"pid":"GW6-S","t":"GASPLANET","wic":{},"woc":{},"wgc":{},"sig":[{"TypeName":"0-2","SigString":"","Dev":{"X":-0.6787240456609758,"Y":-0.3694915489475631}},{"TypeName":"1-3","SigString":"","Dev":{"X":0.12212365683500806,"Y":-0.1009065748417775}},{"TypeName":"3-1","SigString":"","Dev":{"X":-0.762854685115727,"Y":-0.2591165439321537}},{"TypeName":"6-3","SigString":"","Dev":{"X":0.3182073701878279,"Y":-0.6871862395936298}},{"TypeName":"11-1","SigString":"","Dev":{"X":0.2007837278016551,"Y":0.5486252253075135}}],"clr":{"R":207,"G":240,"B":189,"A":255}},"GW6-619":{"pid":"GW6-S","t":"GASPLANET","wic":{},"woc":{},"wgc":{},"sig":[{"TypeName":"0-3","SigString":"","Dev":{"X":-0.189371587700038,"Y":0.5997643490186301}},{"TypeName":"1-3","SigString":"","Dev":{"X":0.29499335509193003,"Y":-0.6034858505728462}},{"TypeName":"3-1","SigString":"","Dev":{"X":-0.3938993636287011,"Y":-0.5637814399937334}},{"TypeName":"6-2","SigString":"","Dev":{"X":-0.9000288353134936,"Y":0.10582671474603492}},{"TypeName":"7-3","SigString":"","Dev":{"X":-0.8811658765779056,"Y":-0.3439224526392446}},{"TypeName":"8-1","SigString":"","Dev":{"X":-0.16893615829455721,"Y":0.7051879930321219}},{"TypeName":"11-1","SigString":"","Dev":{"X":0.5704221348780264,"Y":0.35070641138465547}}],"clr":{"R":253,"G":253,"B":254,"A":255}},"GW6-S":{"t":"STAR","wic":{},"woc":{},"wgc":{},"clr":{"R":233,"G":250,"B":210,"A":255}}}}